README.md
setup.py
dancingcell/__init__.py
dancingcell.egg-info/PKG-INFO
dancingcell.egg-info/SOURCES.txt
dancingcell.egg-info/dependency_links.txt
dancingcell.egg-info/entry_points.txt
dancingcell.egg-info/not-zip-safe
dancingcell.egg-info/requires.txt
dancingcell.egg-info/top_level.txt
dancingcell/constant/__init__.py
dancingcell/constant/constant_properties.py
dancingcell/constant/constant_units.py
dancingcell/core/__init__.py
dancingcell/core/atom.py
dancingcell/core/atoms.py
dancingcell/core/cell.py
dancingcell/core/cellsite.py
dancingcell/core/element.py
dancingcell/core/lattice.py
dancingcell/core/neighbor.py
dancingcell/core/simple_element.py
dancingcell/core/test_unit/__init__.py
dancingcell/core/test_unit/test_atom.py
dancingcell/core/test_unit/test_atoms.py
dancingcell/core/test_unit/test_cell.py
dancingcell/core/test_unit/test_cellsite.py
dancingcell/core/test_unit/test_lattice.py
dancingcell/dash/__init__.py
dancingcell/dash/d1.py
dancingcell/dash/d2.py
dancingcell/lammps/__init__.py
dancingcell/lammps/data.py
dancingcell/lammps/io.py
dancingcell/lammps/unittest/__init__.py
dancingcell/lammps/unittest/test_data.py
dancingcell/lammps/unittest/test_lammpstraj.py
dancingcell/mongodb/__init__.py
dancingcell/mongodb/dancingdb.py
dancingcell/mongodb/unittest/__init__.py
dancingcell/mongodb/unittest/test_db.py
dancingcell/utility/__init__.py
dancingcell/utility/auxbool_argparse.py
dancingcell/utility/dcjson.py
dancingcell/utility/io_file.py
dancingcell/utility/learn_dcjson.py
dancingcell/utility/plt_periodic.py
dancingcell/utility/seaborn_multi_subplot.py
dancingcell/utility/test_pathlib.py
dancingcell/utility/tools.py
dancingcell/utility/unit_test.py
dancingcell/utility/unit_test/__init__.py
dancingcell/utility/unit_test/test_array2d.py
dancingcell/vasp/__init__.py
dancingcell/vasp/bppb.py
dancingcell/vasp/poscar.py
dancingcell/vasp/test_plt.py
dancingcell/vasp/tmp.py
dancingcell/vasp/vasp_band.py
dancingcell/vasp/vasp_dos.py
dancingcell/vasp/xdatcar.py
dancingcell/vasp/xsf.py
dancingcell/vasp/unit_test/__init__.py
dancingcell/vasp/unit_test/test_poscar.py
dancingcell/vasp/unit_test/test_xdatcar.py
dancingcell/vasp/unit_test/test_xsf.py