Metadata-Version: 2.1
Name: dancingcell
Version: 0.0.3b2
Summary: DancingCell of Structures
Home-page: https://gitee.com/alkemiems/dancingcell
Author: Guanjie Wang
Author-email: gjwang@buaa.edu.cn
License: MIT
Platform: UNKNOWN
